tool.py
ashes814/__init__.py
ashes814/ashescool.py
ashes814-1.0.0.dist-info/LICENSE.txt
ashes814-1.0.0.dist-info/METADATA
ashes814-1.0.0.dist-info/WHEEL
ashes814-1.0.0.dist-info/top_level.txt
ashes814-1.0.0.dist-info/RECORD
