Metadata-Version: 2.1
Name: ashes814
Version: 1.0.0
Summary: It is a really niubi package!
Home-page: https://github.com/Ashes814
Author: Ashes
Author-email: 1534661514@qq.com
License: MIT
Platform: UNKNOWN
License-File: LICENSE.txt
